{
  "id": 17606,
  "gender": 1,
  "name": "Imogen Poots",
  "tmdbId": 17606,
  "imdbID": "nm1782299",
  "biography": "Imogen Poots (née le 3 juin 1989) est une actrice anglaise. Elle est surtout connue pour jouer à Tammy dans 28 semaines plus tard. Poots est apparu à l'écran dans un épisode de Casualty et avait un rôle non-parlé dans V pour Vendetta, mais elle était largement inconnue quand, à l'âge de 17 ans, Juan Carlos Fresnadillo la jeta dans 28 semaines plus tard. Depuis lors, elle est apparue dans des films tels que Cracks, Centurion, et le remake 2011 de Fright Night. Bien que Poots n'ait jamais suivi une formation d'actrice, selon Giles Hattersley, un apprentissage pratique peut l'avoir bien servie, car elle est «naturellement fascinante» devant la caméra.",
  "deathDay": null,
  "birthDay": "1989-06-03",
  "birthPlace": "London, England, UK",
  "homepage": null,
  "popularity": 2.7363,
  "imdbId": "nm1782299",
  "wikidataId": "Q237012",
  "wikiDescription": "actrice britannique"
}