{
  "id": 599,
  "title": "Boulevard du crépuscule",
  "originalTitle": "Sunset Boulevard",
  "genres": [
    18
  ],
  "releaseYear": 1950,
  "trailerSource": "",
  "isLocal": false,
  "movieSource": "",
  "synopsis": "Norma Desmond, grande actrice du muet, vit recluse dans sa luxueuse villa de Berverly Hills en compagnie de Max von Meyerling, son majordome qui fut aussi son metteur en scène et mari. Joe Gillis, un scénariste sans le sou, pénètre par hasard dans la propriété et Norma lui propose de travailler au scénario du film qui marquera son retour à l'écran, Salomé. Joe accepte, s'installe chez elle, à la fois fasciné et effrayé par ses extravagances et son délire, et devient bientôt son amant. Quand son délire se transforme en paranoïa et qu'elle débarque au milieu des studios Paramount pour convaincre Cecil B. DeMille de tourner à nouveau avec elle, Gillis commence à prendre ses distances...",
  "tagLine": "Elle a acheté un jeune homme pour satisfaire ses désirs de femme mature",
  "popularity": 33.558,
  "vote": 8.323
}